tests/__init__.py
hercules-0.0.dist-info/RECORD
hercules-0.0.dist-info/METADATA
hercules-0.0.dist-info/metadata.json
hercules-0.0.dist-info/WHEEL
hercules-0.0.dist-info/DESCRIPTION.rst
hercules-0.0.dist-info/top_level.txt
hercules/decorators.py
hercules/lazylist.py
hercules/dict.py
hercules/loop_interface.py
hercules/__init__.py
hercules/tokentype.py
hercules/trie.py
hercules/stream.py
hercules/utils.py
