Metadata-Version: 1.0
Name: hercules
Version: 0.0
Summary: handy tools for strengthy domination
Home-page: http://github.com/twneale/hercules
Author: Thom Neale
Author-email: twneale@gmail.com
License: UNKNOWN
Platform: any
